[
    {
        "timestamp": 8500
    },
    {
        "timestamp": 9000
    },
    {
        "timestamp": 9500
    },
    {
        "timestamp": 10000
    },
    {
        "timestamp": 10500
    },
    {
        "timestamp": 11000
    },
    {
        "timestamp": 11500
    },
    {
        "timestamp": 12000
    },
    {
        "timestamp": 12500
    },
    {
        "timestamp": 13000
    },
    {
        "timestamp": 13500
    },
    {
        "timestamp": 14000
    },
    {
        "timestamp": 14500
    },
    {
        "timestamp": 16500
    },
    {
        "timestamp": 17000
    },
    {
        "timestamp": 17500
    },
    {
        "timestamp": 17666
    },
    {
        "timestamp": 17833
    },
    {
        "timestamp": 18000
    },
    {
        "timestamp": 18500
    },
    {
        "timestamp": 19000
    },
    {
        "timestamp": 19500
    },
    {
        "timestamp": 20000
    },
    {
        "timestamp": 20500
    },
    {
        "timestamp": 21000
    },
    {
        "timestamp": 21500
    },
    {
        "timestamp": 21666
    },
    {
        "timestamp": 21833
    },
    {
        "timestamp": 22000
    },
    {
        "timestamp": 22500
    },
    {
        "timestamp": 23000
    },
    {
        "timestamp": 23500
    },
    {
        "timestamp": 24000
    },
    {
        "timestamp": 24500
    },
    {
        "timestamp": 25000
    },
    {
        "timestamp": 25500
    },
    {
        "timestamp": 25666
    },
    {
        "timestamp": 25833
    },
    {
        "timestamp": 26000
    },
    {
        "timestamp": 26500
    },
    {
        "timestamp": 27000
    },
    {
        "timestamp": 27500
    },
    {
        "timestamp": 28000
    },
    {
        "timestamp": 28500
    },
    {
        "timestamp": 29000
    },
    {
        "timestamp": 29500
    },
    {
        "timestamp": 29666
    },
    {
        "timestamp": 29833
    },
    {
        "timestamp": 30000
    },
    {
        "timestamp": 32500
    },
    {
        "timestamp": 33000
    },
    {
        "timestamp": 33500
    },
    {
        "timestamp": 33666
    },
    {
        "timestamp": 33833
    },
    {
        "timestamp": 34000
    },
    {
        "timestamp": 34500
    },
    {
        "timestamp": 35000
    },
    {
        "timestamp": 35500
    },
    {
        "timestamp": 35666
    },
    {
        "timestamp": 35833
    },
    {
        "timestamp": 36000
    },
    {
        "timestamp": 36500
    },
    {
        "timestamp": 37000
    },
    {
        "timestamp": 37500
    },
    {
        "timestamp": 37666
    },
    {
        "timestamp": 37833
    },
    {
        "timestamp": 38000
    },
    {
        "timestamp": 38500
    },
    {
        "timestamp": 39000
    },
    {
        "timestamp": 39500
    },
    {
        "timestamp": 39666
    },
    {
        "timestamp": 39833
    },
    {
        "timestamp": 40000
    },
    {
        "timestamp": 40500
    },
    {
        "timestamp": 41000
    },
    {
        "timestamp": 41500
    },
    {
        "timestamp": 41666
    },
    {
        "timestamp": 41833
    },
    {
        "timestamp": 42000
    },
    {
        "timestamp": 42500
    },
    {
        "timestamp": 43000
    },
    {
        "timestamp": 43500
    },
    {
        "timestamp": 43666
    },
    {
        "timestamp": 43833
    },
    {
        "timestamp": 44000
    },
    {
        "timestamp": 44500
    },
    {
        "timestamp": 45000
    },
    {
        "timestamp": 45500
    },
    {
        "timestamp": 45666
    },
    {
        "timestamp": 45833
    },
    {
        "timestamp": 46000
    },
    {
        "timestamp": 47000
    },
    {
        "timestamp": 47500
    },
    {
        "timestamp": 48000
    }
]